{
  "Workflows": [
    {
      "Path": null,
      "SortBy": 0,
      "VariablesSectionElementsOrder": [],
      "ArgumentsSectionElementsOrder": null,
      "ConstantsSectionElementsOrder": [],
      "AddedNamespaces": null
    },
    {
      "Path": "Main.xaml",
      "SortBy": 0,
      "VariablesSectionElementsOrder": [
        "dt1&Sequence_1",
        "dtAsString&Sequence_1",
        "DateTime&Sequence_1",
        "dt&Sequence_1"
      ],
      "ArgumentsSectionElementsOrder": [],
      "ConstantsSectionElementsOrder": [],
      "AddedNamespaces": null
    },
    {
      "Path": "convertDateFromExcelToDateFormatInUipath.xaml",
      "SortBy": 0,
      "VariablesSectionElementsOrder": [
        "duedate&Sequence_1",
        "duedateAsString&Sequence_1",
        "dt&Sequence_1"
      ],
      "ArgumentsSectionElementsOrder": [],
      "ConstantsSectionElementsOrder": [],
      "AddedNamespaces": null
    }
  ]
}